{"cameraMode":{"drawMode":0,"name":"Shaded","section":"Shading Mode"},"sceneLighting":true,"audioPlay":false,"sceneViewState":{"m_AlwaysRefresh":false,"showFog":true,"showSkybox":true,"showFlares":true,"showImageEffects":true,"showParticleSystems":true,"showVisualEffectGraphs":true,"m_FxEnabled":true},"in2DMode":false,"pivot":{"x":7.435239791870117,"y":-2.5228326320648195,"z":8.504585266113282},"rotation":{"x":0.14444059133529664,"y":0.3549559414386749,"z":-0.05560530722141266,"w":0.9219867587089539},"size":7.574102401733398,"orthographic":false}